qgriff/__init__.py
qgriff/qgriff.py
quaggagriff-0.1.5.dist-info/LICENSE
quaggagriff-0.1.5.dist-info/METADATA
quaggagriff-0.1.5.dist-info/WHEEL
quaggagriff-0.1.5.dist-info/top_level.txt
quaggagriff-0.1.5.dist-info/RECORD
