Metadata-Version: 2.1
Name: quaggagriff
Version: 0.1.5
Summary: A Discord bot for naturalists
Home-page: https://github.com/synrg/quaggagriff
Author: Ben Armstrong
Author-email: synrg@debian.org
License: UNKNOWN
Platform: UNKNOWN
Classifier: Programming Language :: Python :: 3
Classifier: License :: OSI Approved :: MIT License
Classifier: Operating System :: OS Independent
Requires-Dist: appdirs (<2,>=1.4.3)
Requires-Dist: ebird-api (<4,>=3.0.4)
Requires-Dist: discord.py (<2,>=1.2.3)
Requires-Dist: tzlocal (<3,>=2.0.0)
